MANIFEST.in
README.md
README.rst
setup.cfg
setup.py
ibu/__init__.py
ibu/cli.py
ibu/config.py
ibu/connection.py
ibu/dump.py
ibu/inspect.py
ibu/load.py
ibu.egg-info/PKG-INFO
ibu.egg-info/SOURCES.txt
ibu.egg-info/dependency_links.txt
ibu.egg-info/entry_points.txt
ibu.egg-info/requires.txt
ibu.egg-info/top_level.txt